drf_fullclean/__init__.py
drf_fullclean/serializers.py
drf_fullclean/utils.py
drf_fullclean-0.0.3.dist-info/LICENSE
drf_fullclean-0.0.3.dist-info/METADATA
drf_fullclean-0.0.3.dist-info/WHEEL
drf_fullclean-0.0.3.dist-info/top_level.txt
drf_fullclean-0.0.3.dist-info/RECORD
