Metadata-Version: 2.1
Name: drf-fullclean
Version: 0.0.3
Summary: Call django model full_clean() when validate ModelSerializer
Home-page: https://github.com/giuseppenovielli/drf-fullclean
Author: Giuseppe Novielli
Author-email: novielligiuseppe@gmail.com
License: MIT License
Project-URL: Documentation, https://github.com/giuseppenovielli/drf-fullclean?tab=readme-ov-file#drf-fullclean
Project-URL: Funding, https://buymeacoffee.com/giuseppedev
Project-URL: Source, https://github.com/giuseppenovielli/drf-fullclean
Project-URL: Tracker, https://github.com/giuseppenovielli/drf-fullclean/issues
Keywords: django-rest-framework,model-serializer,validate,full_clean
Classifier: Programming Language :: Python :: 3
Classifier: License :: OSI Approved :: MIT License
Classifier: Operating System :: OS Independent
Classifier: Environment :: Web Environment
Classifier: Framework :: Django
Classifier: Intended Audience :: Developers
Classifier: Operating System :: OS Independent
Classifier: Development Status :: 1 - Planning
Requires-Python: >=3.7
License-File: LICENSE
